{"Poland": {"name": "Republic of Poland", "capital": "Warsaw", "region": "Europe", "population": 37970000, "languages": "Polish", "currencies": "Polish z\u0142oty (PLN)"}, "Sweden": {"name": "Kingdom of Sweden", "capital": ["Stockholm"], "region": "Europe", "population": 10353442, "languages": {"swe": "Swedish"}, "currency": {"SEK": {"name": "Swedish krona", "symbol": "kr"}}}, "Germany": {"name": "Federal Republic of Germany", "capital": ["Berlin"], "region": "Europe", "population": 83240525, "languages": {"deu": "German"}, "currency": {"EUR": {"name": "Euro", "symbol": "\u20ac"}}}, "Norway": {"name": "Kingdom of Norway", "capital": ["Oslo"], "region": "Europe", "population": 5379475, "languages": {"nno": "Norwegian Nynorsk", "nob": "Norwegian Bokm\u00e5l", "smi": "Sami"}, "currency": {"NOK": {"name": "Norwegian krone", "symbol": "kr"}}}, "Russia": {"name": "Russia", "capital": "Moscow", "region": "Euroe", "population": 15000000, "languages": "russian", "currency": "Rubel"}, "Polska": {"name": "Republic of Poland", "capital": ["Warsaw"], "region": "Europe", "population": 37950802, "languages": {"pol": "Polish"}, "currency": {"PLN": {"name": "Polish z\u0142oty", "symbol": "z\u0142"}}}}